{
  "name": "944",
  "timeTable": [
    {
      "timePoint": 1451628000000,
      "found": [
        {
          "time": 0,
          "arrival_time": "09:39:00",
          "departure_time": "09:39:00",
          "stop_sequence": "0"
        },
        {
          "time": 0.000059999999999999995,
          "arrival_time": "09:40:00",
          "departure_time": "09:40:00",
          "stop_sequence": "1"
        },
        {
          "time": 0.00011999999999999999,
          "arrival_time": "09:41:00",
          "departure_time": "09:41:00",
          "stop_sequence": "2"
        },
        {
          "time": 0.00017999999999999998,
          "arrival_time": "09:42:00",
          "departure_time": "09:42:00",
          "stop_sequence": "3"
        },
        {
          "time": 0.00023999999999999998,
          "arrival_time": "09:43:00",
          "departure_time": "09:43:00",
          "stop_sequence": "4"
        },
        {
          "time": 0.0003,
          "arrival_time": "09:44:00",
          "departure_time": "09:44:00",
          "stop_sequence": "5"
        },
        {
          "time": 0.00035999999999999997,
          "arrival_time": "09:45:00",
          "departure_time": "09:45:00",
          "stop_sequence": "6"
        },
        {
          "time": 0.00047999999999999996,
          "arrival_time": "09:47:00",
          "departure_time": "09:47:00",
          "stop_sequence": "7"
        },
        {
          "time": 0.00054,
          "arrival_time": "09:48:00",
          "departure_time": "09:48:00",
          "stop_sequence": "8"
        },
        {
          "time": 0.00066,
          "arrival_time": "09:50:00",
          "departure_time": "09:50:00",
          "stop_sequence": "9"
        },
        {
          "time": 0.00078,
          "arrival_time": "09:52:00",
          "departure_time": "09:52:00",
          "stop_sequence": "10"
        },
        {
          "time": 0.00102,
          "arrival_time": "09:56:00",
          "departure_time": "09:56:00",
          "stop_sequence": "11"
        },
        {
          "time": 0.00108,
          "arrival_time": "09:57:00",
          "departure_time": "09:57:00",
          "stop_sequence": "12"
        },
        {
          "time": 0.0012,
          "arrival_time": "09:59:00",
          "departure_time": "09:59:00",
          "stop_sequence": "13"
        },
        {
          "time": 0.00126,
          "arrival_time": "10:00:00",
          "departure_time": "10:00:00",
          "stop_sequence": "14"
        },
        {
          "time": 0.00156,
          "arrival_time": "10:05:00",
          "departure_time": "10:05:00",
          "stop_sequence": "15"
        },
        {
          "time": 0.0018,
          "arrival_time": "10:09:00",
          "departure_time": "10:09:00",
          "stop_sequence": "16"
        },
        {
          "time": 0.0019199999999999998,
          "arrival_time": "10:11:00",
          "departure_time": "10:11:00",
          "stop_sequence": "17"
        },
        {
          "time": 0.00198,
          "arrival_time": "10:12:00",
          "departure_time": "10:12:00",
          "stop_sequence": "18"
        },
        {
          "time": 0.00204,
          "arrival_time": "10:13:00",
          "departure_time": "10:13:00",
          "stop_sequence": "19"
        },
        {
          "time": 0.00222,
          "arrival_time": "10:16:00",
          "departure_time": "10:16:00",
          "stop_sequence": "20"
        },
        {
          "time": 0.00228,
          "arrival_time": "10:17:00",
          "departure_time": "10:17:00",
          "stop_sequence": "21"
        },
        {
          "time": 0.00234,
          "arrival_time": "10:18:00",
          "departure_time": "10:18:00",
          "stop_sequence": "22"
        },
        {
          "time": 0.00246,
          "arrival_time": "10:20:00",
          "departure_time": "10:20:00",
          "stop_sequence": "23"
        },
        {
          "time": 0.00252,
          "arrival_time": "10:21:00",
          "departure_time": "10:21:00",
          "stop_sequence": "24"
        }
      ]
    },
    {
      "timePoint": 1451649600000,
      "found": [
        {
          "time": 0,
          "arrival_time": "09:39:00",
          "departure_time": "09:39:00",
          "stop_sequence": "0"
        },
        {
          "time": 0.000059999999999999995,
          "arrival_time": "09:40:00",
          "departure_time": "09:40:00",
          "stop_sequence": "1"
        },
        {
          "time": 0.00011999999999999999,
          "arrival_time": "09:41:00",
          "departure_time": "09:41:00",
          "stop_sequence": "2"
        },
        {
          "time": 0.00017999999999999998,
          "arrival_time": "09:42:00",
          "departure_time": "09:42:00",
          "stop_sequence": "3"
        },
        {
          "time": 0.00023999999999999998,
          "arrival_time": "09:43:00",
          "departure_time": "09:43:00",
          "stop_sequence": "4"
        },
        {
          "time": 0.0003,
          "arrival_time": "09:44:00",
          "departure_time": "09:44:00",
          "stop_sequence": "5"
        },
        {
          "time": 0.00035999999999999997,
          "arrival_time": "09:45:00",
          "departure_time": "09:45:00",
          "stop_sequence": "6"
        },
        {
          "time": 0.00047999999999999996,
          "arrival_time": "09:47:00",
          "departure_time": "09:47:00",
          "stop_sequence": "7"
        },
        {
          "time": 0.00054,
          "arrival_time": "09:48:00",
          "departure_time": "09:48:00",
          "stop_sequence": "8"
        },
        {
          "time": 0.00066,
          "arrival_time": "09:50:00",
          "departure_time": "09:50:00",
          "stop_sequence": "9"
        },
        {
          "time": 0.00078,
          "arrival_time": "09:52:00",
          "departure_time": "09:52:00",
          "stop_sequence": "10"
        },
        {
          "time": 0.00102,
          "arrival_time": "09:56:00",
          "departure_time": "09:56:00",
          "stop_sequence": "11"
        },
        {
          "time": 0.00108,
          "arrival_time": "09:57:00",
          "departure_time": "09:57:00",
          "stop_sequence": "12"
        },
        {
          "time": 0.0012,
          "arrival_time": "09:59:00",
          "departure_time": "09:59:00",
          "stop_sequence": "13"
        },
        {
          "time": 0.00126,
          "arrival_time": "10:00:00",
          "departure_time": "10:00:00",
          "stop_sequence": "14"
        },
        {
          "time": 0.00156,
          "arrival_time": "10:05:00",
          "departure_time": "10:05:00",
          "stop_sequence": "15"
        },
        {
          "time": 0.0018,
          "arrival_time": "10:09:00",
          "departure_time": "10:09:00",
          "stop_sequence": "16"
        },
        {
          "time": 0.0019199999999999998,
          "arrival_time": "10:11:00",
          "departure_time": "10:11:00",
          "stop_sequence": "17"
        },
        {
          "time": 0.00198,
          "arrival_time": "10:12:00",
          "departure_time": "10:12:00",
          "stop_sequence": "18"
        },
        {
          "time": 0.00204,
          "arrival_time": "10:13:00",
          "departure_time": "10:13:00",
          "stop_sequence": "19"
        },
        {
          "time": 0.00222,
          "arrival_time": "10:16:00",
          "departure_time": "10:16:00",
          "stop_sequence": "20"
        },
        {
          "time": 0.00228,
          "arrival_time": "10:17:00",
          "departure_time": "10:17:00",
          "stop_sequence": "21"
        },
        {
          "time": 0.00234,
          "arrival_time": "10:18:00",
          "departure_time": "10:18:00",
          "stop_sequence": "22"
        },
        {
          "time": 0.00246,
          "arrival_time": "10:20:00",
          "departure_time": "10:20:00",
          "stop_sequence": "23"
        },
        {
          "time": 0.00252,
          "arrival_time": "10:21:00",
          "departure_time": "10:21:00",
          "stop_sequence": "24"
        }
      ]
    },
    {
      "timePoint": 1451658600000,
      "found": [
        {
          "time": 0,
          "arrival_time": "09:39:00",
          "departure_time": "09:39:00",
          "stop_sequence": "0"
        },
        {
          "time": 0.000059999999999999995,
          "arrival_time": "09:40:00",
          "departure_time": "09:40:00",
          "stop_sequence": "1"
        },
        {
          "time": 0.00011999999999999999,
          "arrival_time": "09:41:00",
          "departure_time": "09:41:00",
          "stop_sequence": "2"
        },
        {
          "time": 0.00017999999999999998,
          "arrival_time": "09:42:00",
          "departure_time": "09:42:00",
          "stop_sequence": "3"
        },
        {
          "time": 0.00023999999999999998,
          "arrival_time": "09:43:00",
          "departure_time": "09:43:00",
          "stop_sequence": "4"
        },
        {
          "time": 0.0003,
          "arrival_time": "09:44:00",
          "departure_time": "09:44:00",
          "stop_sequence": "5"
        },
        {
          "time": 0.00035999999999999997,
          "arrival_time": "09:45:00",
          "departure_time": "09:45:00",
          "stop_sequence": "6"
        },
        {
          "time": 0.00047999999999999996,
          "arrival_time": "09:47:00",
          "departure_time": "09:47:00",
          "stop_sequence": "7"
        },
        {
          "time": 0.00054,
          "arrival_time": "09:48:00",
          "departure_time": "09:48:00",
          "stop_sequence": "8"
        },
        {
          "time": 0.00066,
          "arrival_time": "09:50:00",
          "departure_time": "09:50:00",
          "stop_sequence": "9"
        },
        {
          "time": 0.00078,
          "arrival_time": "09:52:00",
          "departure_time": "09:52:00",
          "stop_sequence": "10"
        },
        {
          "time": 0.00102,
          "arrival_time": "09:56:00",
          "departure_time": "09:56:00",
          "stop_sequence": "11"
        },
        {
          "time": 0.00108,
          "arrival_time": "09:57:00",
          "departure_time": "09:57:00",
          "stop_sequence": "12"
        },
        {
          "time": 0.0012,
          "arrival_time": "09:59:00",
          "departure_time": "09:59:00",
          "stop_sequence": "13"
        },
        {
          "time": 0.00126,
          "arrival_time": "10:00:00",
          "departure_time": "10:00:00",
          "stop_sequence": "14"
        },
        {
          "time": 0.00156,
          "arrival_time": "10:05:00",
          "departure_time": "10:05:00",
          "stop_sequence": "15"
        },
        {
          "time": 0.0018,
          "arrival_time": "10:09:00",
          "departure_time": "10:09:00",
          "stop_sequence": "16"
        },
        {
          "time": 0.0019199999999999998,
          "arrival_time": "10:11:00",
          "departure_time": "10:11:00",
          "stop_sequence": "17"
        },
        {
          "time": 0.00198,
          "arrival_time": "10:12:00",
          "departure_time": "10:12:00",
          "stop_sequence": "18"
        },
        {
          "time": 0.00204,
          "arrival_time": "10:13:00",
          "departure_time": "10:13:00",
          "stop_sequence": "19"
        },
        {
          "time": 0.00222,
          "arrival_time": "10:16:00",
          "departure_time": "10:16:00",
          "stop_sequence": "20"
        },
        {
          "time": 0.00228,
          "arrival_time": "10:17:00",
          "departure_time": "10:17:00",
          "stop_sequence": "21"
        },
        {
          "time": 0.00234,
          "arrival_time": "10:18:00",
          "departure_time": "10:18:00",
          "stop_sequence": "22"
        },
        {
          "time": 0.00246,
          "arrival_time": "10:20:00",
          "departure_time": "10:20:00",
          "stop_sequence": "23"
        },
        {
          "time": 0.00252,
          "arrival_time": "10:21:00",
          "departure_time": "10:21:00",
          "stop_sequence": "24"
        }
      ]
    }
  ]
}